odoo/addons/sm_rewards_rest_api/__init__.py
odoo/addons/sm_rewards_rest_api/__manifest__.py
odoo/addons/sm_rewards_rest_api/models/__init__.py
odoo/addons/sm_rewards_rest_api/models/models_sm_reward.py
odoo/addons/sm_rewards_rest_api/services/__init__.py
odoo/addons/sm_rewards_rest_api/services/schemas.py
odoo/addons/sm_rewards_rest_api/services/services_sm_reward.py
odoo12_addon_sm_rewards_rest_api-12.0.0.0.3.dist-info/METADATA
odoo12_addon_sm_rewards_rest_api-12.0.0.0.3.dist-info/WHEEL
odoo12_addon_sm_rewards_rest_api-12.0.0.0.3.dist-info/top_level.txt
odoo12_addon_sm_rewards_rest_api-12.0.0.0.3.dist-info/RECORD
