Metadata-Version: 2.1
Name: odoo12-addon-sm-rewards-rest-api
Version: 12.0.0.0.3
Summary: REST API for carsharing rewards
Home-page: https://www.sommobilitat.coop
Author: Som Mobilitat
License: UNKNOWN
Platform: UNKNOWN
Classifier: Programming Language :: Python
Classifier: Framework :: Odoo
Requires-Python: >=3.5
Requires-Dist: odoo12-addon-easy-my-coop-api
Requires-Dist: odoo12-addon-sm-rewards
Requires-Dist: odoo (<12.1dev,>=12.0a)
